pyplr/CIE.py
pyplr/__init__.py
pyplr/calibrate.py
pyplr/graphing.py
pyplr/jeti.py
pyplr/leduino.py
pyplr/oceanops.py
pyplr/plr.py
pyplr/preproc.py
pyplr/protocol.py
pyplr/pupil.py
pyplr/pupil_old.py
pyplr/silentsub.py
pyplr/spectools.py
pyplr/stlab.py
pyplr/utils.py
pyplr/test/__init__.py
pyplr/test/test.py
pyplr-1.0.1.dist-info/LICENSE.txt
pyplr-1.0.1.dist-info/METADATA
pyplr-1.0.1.dist-info/WHEEL
pyplr-1.0.1.dist-info/top_level.txt
pyplr-1.0.1.dist-info/RECORD
