Metadata-Version: 2.1
Name: pyplr
Version: 1.0.1
Summary: Software for researching the pupillary light reflex
Home-page: https://github.com/PyPlr/cvd_pupillometry
Author: Joel T. Martin
Author-email: joel.t.martin36@gmail.com
License: UNKNOWN
Project-URL: Documentation, https://pyplr.github.io/cvd_pupillometry/
Project-URL: bioRxiv preprint, https://www.biorxiv.org/content/10.1101/2021.06.02.446731v2
Platform: UNKNOWN
Classifier: Development Status :: 5 - Production/Stable
Classifier: Topic :: Scientific/Engineering :: Information Analysis
Classifier: License :: OSI Approved :: MIT License
Classifier: Intended Audience :: Science/Research
Classifier: Programming Language :: Python :: 3.7
License-File: LICENSE.txt
Requires-Dist: scipy
Requires-Dist: matplotlib
Requires-Dist: msgpack
Requires-Dist: pyzmq
Requires-Dist: requests
Requires-Dist: numpy
Requires-Dist: seaborn
Requires-Dist: seabreeze
Requires-Dist: numexpr
Requires-Dist: tables
Requires-Dist: pandas
